cconn/__init__.py
cconn/connection.py
cconn/connection_factory.py
cconn/module.py
cconn/server.py
cconn/bus/__init__.py
cconn/bus/bus.py
cconn/bus/cross_connection_bus.py
cconn/bus/server_struct.py
cconn/comm/__init__.py
cconn/comm/base/__init__.py
cconn/comm/base/comm.py
cconn/comm/base/comm_handler.py
cconn/comm/base/comm_server_wrapper.py
cconn/comm/base/msg.py
cconn/comm/base/topic_mapper.py
cconn/comm/base/pubsub/__init__.py
cconn/comm/base/pubsub/client_comm_pubsub_manager.py
cconn/comm/base/pubsub/server_comm_pubsub_manager.py
cconn/comm/base/pubsub/subscription.py
cconn/comm/tcp/__init__.py
cconn/comm/tcp/tcp_comm.py
cconn/comm/tcp/client/__init__.py
cconn/comm/tcp/client/tcp_client.py
cconn/comm/tcp/server/__init__.py
cconn/comm/tcp/server/tcp_server.py
cconn/definitions/__init__.py
cconn/definitions/constants.py
cconn/definitions/prop_keys.py
cconn/definitions/types.py
cconn/log/__init__.py
cconn/log/logger.py
cconn/network/__init__.py
cconn/network/detect/__init__.py
cconn/network/detect/network_detector.py
cconn/network/detect/udp/__init__.py
cconn/network/detect/udp/broadcast_header.py
cconn/network/detect/udp/udp_detector.py
cconn/network/register/__init__.py
cconn/network/register/network_register.py
cconn/network/register/udp/__init__.py
cconn/network/register/udp/udp_register.py
cconn/utils/__init__.py
cconn/utils/address_utils.py
cconn/utils/data_converter.py
cconn/utils/msg_thread.py
cconn/utils/props.py
cconn/utils/str.py
cconn/utils/time.py
cconn/utils/topic_utils.py
tests/__init__.py
tests/test_comm_handler.py
tests/test_ip_utils.py
tests/test_msg.py
tests/test_msg_thread.py
tests/test_topic_mapper.py
tests/test_topic_utils.py
cross_connection-0.2.7.dist-info/LICENSE.md
cross_connection-0.2.7.dist-info/METADATA
cross_connection-0.2.7.dist-info/WHEEL
cross_connection-0.2.7.dist-info/top_level.txt
cross_connection-0.2.7.dist-info/RECORD
