Metadata-Version: 2.1
Name: cross-connection
Version: 0.2.7
Summary: cross-connection library
Author: Jie Meng
Author-email: jiemeng@thoughtworks.com
License: Apache 2.0
License-File: LICENSE.md
